metabolicsexamplepackage/__init__.py
metabolicsexamplepackage/hello_pandas.py
metabolicsexamplepackage-0.1.0.dist-info/WHEEL
metabolicsexamplepackage-0.1.0.dist-info/METADATA
metabolicsexamplepackage-0.1.0.dist-info/RECORD
