Metadata-Version: 2.1
Name: metabolicsexamplepackage
Version: 0.1.0
Summary: 
Author: Ivan Thung
Author-email: ivanthung@gmail.com
Requires-Python: >=3.09,<4.0
Classifier: Programming Language :: Python :: 3
Classifier: Programming Language :: Python :: 3.9
Classifier: Programming Language :: Python :: 3.10
Classifier: Programming Language :: Python :: 3.11
Requires-Dist: pandas (>=2.0.0,<3.0.0)
Requires-Dist: requests (>=2.28.2,<3.0.0)
